textual_pyfiglet_fonts/1943____.flf
textual_pyfiglet_fonts/1row.flf
textual_pyfiglet_fonts/3-d.flf
textual_pyfiglet_fonts/3d-ascii.flf
textual_pyfiglet_fonts/3d_diagonal.flf
textual_pyfiglet_fonts/3x5.flf
textual_pyfiglet_fonts/4max.flf
textual_pyfiglet_fonts/4x4_offr.flf
textual_pyfiglet_fonts/5lineoblique.flf
textual_pyfiglet_fonts/64f1____.flf
textual_pyfiglet_fonts/6x10.flf
textual_pyfiglet_fonts/__init__.py
textual_pyfiglet_fonts/a_zooloo.flf
textual_pyfiglet_fonts/acrobatic.flf
textual_pyfiglet_fonts/advenger.flf
textual_pyfiglet_fonts/alligator.flf
textual_pyfiglet_fonts/alligator2.flf
textual_pyfiglet_fonts/alpha.flf
textual_pyfiglet_fonts/alphabet.flf
textual_pyfiglet_fonts/amc_3_line.flf
textual_pyfiglet_fonts/amc_3_liv1.flf
textual_pyfiglet_fonts/amc_aaa01.flf
textual_pyfiglet_fonts/amc_neko.flf
textual_pyfiglet_fonts/amc_razor.flf
textual_pyfiglet_fonts/amc_razor2.flf
textual_pyfiglet_fonts/amc_slash.flf
textual_pyfiglet_fonts/amc_slider.flf
textual_pyfiglet_fonts/amc_thin.flf
textual_pyfiglet_fonts/amc_tubes.flf
textual_pyfiglet_fonts/amc_untitled.flf
textual_pyfiglet_fonts/ansi_regular.flf
textual_pyfiglet_fonts/ansi_shadow.flf
textual_pyfiglet_fonts/aquaplan.flf
textual_pyfiglet_fonts/arrows.flf
textual_pyfiglet_fonts/asc_____.flf
textual_pyfiglet_fonts/ascii12.tlf
textual_pyfiglet_fonts/ascii9.tlf
textual_pyfiglet_fonts/ascii___.flf
textual_pyfiglet_fonts/ascii_new_roman.flf
textual_pyfiglet_fonts/assalt_m.flf
textual_pyfiglet_fonts/asslt__m.flf
textual_pyfiglet_fonts/atc_____.flf
textual_pyfiglet_fonts/atc_gran.flf
textual_pyfiglet_fonts/avatar.flf
textual_pyfiglet_fonts/b1ff.flf
textual_pyfiglet_fonts/b_m__200.flf
textual_pyfiglet_fonts/banner.flf
textual_pyfiglet_fonts/banner3-D.flf
textual_pyfiglet_fonts/banner3.flf
textual_pyfiglet_fonts/banner4.flf
textual_pyfiglet_fonts/barbwire.flf
textual_pyfiglet_fonts/basic.flf
textual_pyfiglet_fonts/battle_s.flf
textual_pyfiglet_fonts/battlesh.flf
textual_pyfiglet_fonts/baz__bil.flf
textual_pyfiglet_fonts-0.3.1.dist-info/METADATA
textual_pyfiglet_fonts-0.3.1.dist-info/WHEEL
textual_pyfiglet_fonts-0.3.1.dist-info/RECORD
