Metadata-Version: 2.4
Name: textual-pyfiglet-fonts
Version: 0.3.1
Summary: The full extended fonts collection packaged as an optional dependency for textual-pyfiglet
Author-email: edward-jazzhands <ed.jazzhands@gmail.com>
License-Expression: MIT
Requires-Python: >=3.8.1
